setup.py
base_utils/__init__.py
base_utils/dtos.py
base_utils/exception.py
base_utils/utils.py
closehavenbase.egg-info/PKG-INFO
closehavenbase.egg-info/SOURCES.txt
closehavenbase.egg-info/dependency_links.txt
closehavenbase.egg-info/requires.txt
closehavenbase.egg-info/top_level.txt