Metadata-Version: 2.1
Name: closehavenbase
Version: 0.1
Summary: Custom exception handiling 
Home-page: UNKNOWN
Author: Test
Author-email: raj.p@logicrays.com
License: UNKNOWN
Platform: UNKNOWN
